aliyunsdkgdb/__init__.py
aliyunsdkgdb/endpoint.py
aliyunsdkgdb/request/__init__.py
aliyunsdkgdb/request/v20190903/AllocateInstancePublicConnectionRequest.py
aliyunsdkgdb/request/v20190903/CreateAccountRequest.py
aliyunsdkgdb/request/v20190903/CreateDBInstanceRequest.py
aliyunsdkgdb/request/v20190903/CreateServiceLinkedRoleRequest.py
aliyunsdkgdb/request/v20190903/DeleteDBInstanceRequest.py
aliyunsdkgdb/request/v20190903/DescribeAccountsRequest.py
aliyunsdkgdb/request/v20190903/DescribeAvailableResourceRequest.py
aliyunsdkgdb/request/v20190903/DescribeBackupPolicyRequest.py
aliyunsdkgdb/request/v20190903/DescribeBackupsRequest.py
aliyunsdkgdb/request/v20190903/DescribeDBInstanceAccessWhiteListRequest.py
aliyunsdkgdb/request/v20190903/DescribeDBInstanceAttributeRequest.py
aliyunsdkgdb/request/v20190903/DescribeDBInstancePerformanceRequest.py
aliyunsdkgdb/request/v20190903/DescribeDBInstanceStatusRequest.py
aliyunsdkgdb/request/v20190903/DescribeDBInstancesRequest.py
aliyunsdkgdb/request/v20190903/DescribeRegionsRequest.py
aliyunsdkgdb/request/v20190903/DescribeResourceUsageRequest.py
aliyunsdkgdb/request/v20190903/DescribeSecurityGroupConfigurationRequest.py
aliyunsdkgdb/request/v20190903/ModifyBackupPolicyRequest.py
aliyunsdkgdb/request/v20190903/ModifyDBInstanceAccessWhiteListRequest.py
aliyunsdkgdb/request/v20190903/ModifyDBInstanceDescriptionRequest.py
aliyunsdkgdb/request/v20190903/ModifyDBInstanceMaintainTimeRequest.py
aliyunsdkgdb/request/v20190903/ModifySecurityGroupConfigurationRequest.py
aliyunsdkgdb/request/v20190903/ResetAccountPasswordRequest.py
aliyunsdkgdb/request/v20190903/RestartDBInstanceRequest.py
aliyunsdkgdb/request/v20190903/UpgradeDBInstanceKernelVersionRequest.py
aliyunsdkgdb/request/v20190903/__init__.py
aliyun_python_sdk_gdb-1.0.0.dist-info/LICENSE
aliyun_python_sdk_gdb-1.0.0.dist-info/METADATA
aliyun_python_sdk_gdb-1.0.0.dist-info/WHEEL
aliyun_python_sdk_gdb-1.0.0.dist-info/top_level.txt
aliyun_python_sdk_gdb-1.0.0.dist-info/RECORD
